EasyCryptographer/__init__.py
EasyCryptographer/cryptography_program.py
EasyCryptographer/audio/__init__.py
EasyCryptographer/convention/__init__.py
EasyCryptographer/convention/AEAD/AEAD1.py
EasyCryptographer/convention/AEAD/AEAD2.py
EasyCryptographer/convention/AEAD/AEAD3.py
EasyCryptographer/convention/AEAD/AEAD4.py
EasyCryptographer/convention/AEAD/AEAD_method.py
EasyCryptographer/convention/AEAD/__init__.py
EasyCryptographer/convention/AES/AES1.py
EasyCryptographer/convention/AES/AES2.py
EasyCryptographer/convention/AES/AES3.py
EasyCryptographer/convention/AES/AES4.py
EasyCryptographer/convention/AES/AES_method.py
EasyCryptographer/convention/AES/__init__.py
EasyCryptographer/convention/Blowfish/Blowfish1.py
EasyCryptographer/convention/Blowfish/Blowfish2.py
EasyCryptographer/convention/Blowfish/Blowfish3.py
EasyCryptographer/convention/Blowfish/Blowfish4.py
EasyCryptographer/convention/Blowfish/Blowfish_method.py
EasyCryptographer/convention/Blowfish/__init__.py
EasyCryptographer/convention/CAST5/CAST51.py
EasyCryptographer/convention/CAST5/CAST52.py
EasyCryptographer/convention/CAST5/CAST53.py
EasyCryptographer/convention/CAST5/CAST54.py
EasyCryptographer/convention/CAST5/CAST5_method.py
EasyCryptographer/convention/CAST5/__init__.py
EasyCryptographer/convention/Camellia/Camellia1.py
EasyCryptographer/convention/Camellia/Camellia2.py
EasyCryptographer/convention/Camellia/Camellia3.py
EasyCryptographer/convention/Camellia/Camellia4.py
EasyCryptographer/convention/Camellia/Camellia_method.py
EasyCryptographer/convention/Camellia/__init__.py
EasyCryptographer/convention/Fernet/Fernet1.py
EasyCryptographer/convention/Fernet/Fernet2.py
EasyCryptographer/convention/Fernet/Fernet3.py
EasyCryptographer/convention/Fernet/Fernet4.py
EasyCryptographer/convention/Fernet/Fernet_method.py
EasyCryptographer/convention/Fernet/__init__.py
EasyCryptographer/convention/RC4/RC41.py
EasyCryptographer/convention/RC4/RC42.py
EasyCryptographer/convention/RC4/RC43.py
EasyCryptographer-3.4.2.dist-info/LICENSE
EasyCryptographer-3.4.2.dist-info/METADATA
EasyCryptographer-3.4.2.dist-info/WHEEL
EasyCryptographer-3.4.2.dist-info/top_level.txt
EasyCryptographer-3.4.2.dist-info/RECORD
