Metadata-Version: 2.2
Name: EasyCryptographer
Version: 3.4.2
Summary: EasyCryptographer: Let the user encrypt and decrypt easily
Home-page: https://gitee.com/yanxinle1123/EasyCryptographer
Author: YanXinle
Author-email: 1020121123@qq.com
License-File: LICENSE
Dynamic: author
Dynamic: author-email
Dynamic: home-page
Dynamic: summary
